{"type": "FeatureCollection", "features": [{"type": "Feature", "properties": {"name": "\u0424\u0413\u0423\u041f \u041d\u0418\u0418 \u041a\u0412\u0410\u041d\u0422"}, "geometry": {"type": "Point", "coordinates": [55.858488, 37.530023, 0.0]}, "id": "3"}], "name": "index"}